daaayonearth.py
daaayonearth-0.75.dist-info/LICENSE
daaayonearth-0.75.dist-info/METADATA
daaayonearth-0.75.dist-info/WHEEL
daaayonearth-0.75.dist-info/top_level.txt
daaayonearth-0.75.dist-info/RECORD
