Metadata-Version: 2.1
Name: daaayonearth
Version: 0.75
Summary: Easy access to geographic, meteorologic and photovoltaic performance data/services.
Home-page: https://www.blackward.de
Author: Dominik Niedenzu
Author-email: blythooon@blackward.de
Maintainer: Dominik Niedenzu
License: Proprietary License
Platform: any platform which provides python
Classifier: Development Status :: 3 - Alpha
Classifier: Intended Audience :: Developers
Classifier: Intended Audience :: Education
Classifier: Intended Audience :: Science/Research
Classifier: Intended Audience :: Other Audience
Classifier: License :: Other/Proprietary License
Classifier: Operating System :: OS Independent
Classifier: Programming Language :: Python
Classifier: Topic :: Software Development
Requires-Python: >= 2.2
License-File: LICENSE
Requires-Dist: numpy
Requires-Dist: scipy
Requires-Dist: pandas (<=1.4.0)
Requires-Dist: matplotlib
Requires-Dist: geopy
Requires-Dist: timezonefinder
